saasops/__init__.py
saasops/calc.py
saasops/check.py
saasops/classes.py
saasops/constants.py
saasops/database.py
saasops/display.py
saasops/export.py
saasops/main.py
saasops/utils.py
saasops/visualization.py
saasops-0.1.1.dist-info/LICENSE
saasops-0.1.1.dist-info/METADATA
saasops-0.1.1.dist-info/WHEEL
saasops-0.1.1.dist-info/entry_points.txt
saasops-0.1.1.dist-info/RECORD
