Metadata-Version: 2.1
Name: saasops
Version: 0.1.1
Summary: Package for handling recurring revenue reporting in SaaS startups
License: MIT
Author: Johnnie Walker
Author-email: jw12866@gmail.com
Requires-Python: >=3.9,<3.13
Classifier: License :: OSI Approved :: MIT License
Classifier: Programming Language :: Python :: 3
Classifier: Programming Language :: Python :: 3.9
Classifier: Programming Language :: Python :: 3.10
Classifier: Programming Language :: Python :: 3.11
Requires-Dist: Sphinx (>=7.3.7,<8.0.0)
Requires-Dist: babel (==2.12.1)
Requires-Dist: certifi (==2023.7.22)
Requires-Dist: charset-normalizer (==3.2.0)
Requires-Dist: click (==8.1.7)
Requires-Dist: colorama (==0.4.6)
Requires-Dist: contourpy (==1.1.1)
Requires-Dist: cycler (==0.11.0)
Requires-Dist: distlib (==0.3.7)
Requires-Dist: duckdb (==0.9.2)
Requires-Dist: filelock (==3.12.4)
Requires-Dist: fonttools (==4.42.1)
Requires-Dist: ghp-import (==2.1.0)
Requires-Dist: greenlet (==2.0.2)
Requires-Dist: idna (==3.4)
Requires-Dist: jinja2 (==3.1.2)
Requires-Dist: kiwisolver (==1.4.5)
Requires-Dist: lxml (==4.9.3)
Requires-Dist: markdown (==3.4.4)
Requires-Dist: markdown-it-py (==3.0.0)
Requires-Dist: markupsafe (==2.1.3)
Requires-Dist: matplotlib (==3.8.0)
Requires-Dist: mdurl (==0.1.2)
Requires-Dist: mergedeep (==1.3.4)
Requires-Dist: mkdocs (==1.5.3)
Requires-Dist: mkdocs-material (==9.4.2)
Requires-Dist: mkdocs-material-extensions (==1.2)
Requires-Dist: numpy (==1.26.0)
Requires-Dist: packaging (==23.1)
Requires-Dist: paginate (==0.5.6)
Requires-Dist: pandas (==2.1.1)
Requires-Dist: pathspec (==0.11.2)
Requires-Dist: pillow (==9.5.0)
Requires-Dist: pipenv (==2023.9.8)
Requires-Dist: platformdirs (==3.10.0)
Requires-Dist: psycopg2-binary (==2.9.7)
Requires-Dist: pygments (==2.16.1)
Requires-Dist: pymdown-extensions (==10.3)
Requires-Dist: pyparsing (==3.1.1)
Requires-Dist: pytest (>=8.2.2,<9.0.0)
Requires-Dist: python-dateutil (==2.8.2)
Requires-Dist: python-dotenv (==1.0.0)
Requires-Dist: python-pptx (==0.6.22)
Requires-Dist: pytz (==2023.3.post1)
Requires-Dist: pyyaml (==6.0.1)
Requires-Dist: pyyaml-env-tag (==0.1)
Requires-Dist: regex (==2023.8.8)
Requires-Dist: requests (==2.31.0)
Requires-Dist: rich (==13.5.3)
Requires-Dist: six (==1.16.0)
Requires-Dist: sphinx-rtd-theme (>=2.0.0,<3.0.0)
Requires-Dist: sqlalchemy (==2.0.21)
Requires-Dist: twine (>=5.1.1,<6.0.0)
Requires-Dist: typer (==0.9.0)
Requires-Dist: typing-extensions (==4.8.0)
Requires-Dist: tzdata (==2023.3)
Requires-Dist: urllib3 (==2.0.5)
Requires-Dist: virtualenv (==20.24.5)
Requires-Dist: watchdog (==3.0.0)
Requires-Dist: xlsxwriter (==3.1.5)
